mobileprint/__init__.py
mobileprint/arguments.py
mobileprint/human_benchmark.py
mobileprint/storage.py
mobileprint/env/Env1D.py
mobileprint/env/Env2D.py
mobileprint/env/Env3D.py
mobileprint/env/__init__.py
mobileprint_2-0.0.4.dist-info/LICENSE
mobileprint_2-0.0.4.dist-info/METADATA
mobileprint_2-0.0.4.dist-info/WHEEL
mobileprint_2-0.0.4.dist-info/top_level.txt
mobileprint_2-0.0.4.dist-info/RECORD
